{
    "sourceFile": "01-components-basics/src/app/app.component.ts",
    "activeCommit": 0,
    "commits": [
        {
            "activePatchIndex": 14,
            "patches": [
                {
                    "date": 1701855347807,
                    "content": "Index: \n===================================================================\n--- \n+++ \n"
                },
                {
                    "date": 1701855364473,
                    "content": "Index: \n===================================================================\n--- \n+++ \n@@ -2,9 +2,9 @@\n \n @Component({\n   selector: 'app-root',\n   standalone: true,\n-  template: `<h1>Welcome to {{title}}!</h1>`\n+  template: `<h1>Welcome to {{title}}! Hello</h1>`\n })\n \n export class AppComponent {\n   title = '01-components-basics';\n"
                },
                {
                    "date": 1701855496479,
                    "content": "Index: \n===================================================================\n--- \n+++ \n@@ -2,10 +2,11 @@\n \n @Component({\n   selector: 'app-root',\n   standalone: true,\n-  template: `<h1>Welcome to {{title}}! Hello</h1>`\n+  template: `<h1>Welcome to {{title}}! Hello {{name}}</h1>`\n })\n \n export class AppComponent {\n   title = '01-components-basics';\n+  name = 'Adrian'\n }\n"
                },
                {
                    "date": 1701855864976,
                    "content": "Index: \n===================================================================\n--- \n+++ \n@@ -2,11 +2,26 @@\n \n @Component({\n   selector: 'app-root',\n   standalone: true,\n-  template: `<h1>Welcome to {{title}}! Hello {{name}}</h1>`\n+  template: `\n+  <h1>Welcome to {{title}}! Hello {{name}}</h1>\n+  <ul>\n+\n+  </ul>\n+  `\n })\n \n export class AppComponent {\n   title = '01-components-basics';\n-  name = 'Adrian'\n+  name = 'Adrian';\n+  tasks = [\n+    {\n+      name: \"Angular introduction\",\n+      done: false,\n+    },\n+    {\n+      name: \"Learn components\",\n+      done: true\n+    }\n+  ]\n }\n"
                },
                {
                    "date": 1701855917149,
                    "content": "Index: \n===================================================================\n--- \n+++ \n@@ -5,9 +5,9 @@\n   standalone: true,\n   template: `\n   <h1>Welcome to {{title}}! Hello {{name}}</h1>\n   <ul>\n-\n+      <li><button>{{tasks[0]}}</button></li>\n   </ul>\n   `\n })\n \n"
                },
                {
                    "date": 1701855928781,
                    "content": "Index: \n===================================================================\n--- \n+++ \n@@ -5,9 +5,9 @@\n   standalone: true,\n   template: `\n   <h1>Welcome to {{title}}! Hello {{name}}</h1>\n   <ul>\n-      <li><button>{{tasks[0]}}</button></li>\n+      <li><button>{{tasks[0].name}}</button></li>\n   </ul>\n   `\n })\n \n"
                },
                {
                    "date": 1701855954672,
                    "content": "Index: \n===================================================================\n--- \n+++ \n@@ -11,10 +11,9 @@\n   `\n })\n \n export class AppComponent {\n-  title = '01-components-basics';\n-  name = 'Adrian';\n+  title = 'To do list';\n   tasks = [\n     {\n       name: \"Angular introduction\",\n       done: false,\n"
                },
                {
                    "date": 1701855968525,
                    "content": "Index: \n===================================================================\n--- \n+++ \n@@ -3,9 +3,9 @@\n @Component({\n   selector: 'app-root',\n   standalone: true,\n   template: `\n-  <h1>Welcome to {{title}}! Hello {{name}}</h1>\n+  <h1>{{title}}</h1>\n   <ul>\n       <li><button>{{tasks[0].name}}</button></li>\n   </ul>\n   `\n"
                },
                {
                    "date": 1701855988281,
                    "content": "Index: \n===================================================================\n--- \n+++ \n@@ -3,17 +3,17 @@\n @Component({\n   selector: 'app-root',\n   standalone: true,\n   template: `\n-  <h1>{{title}}</h1>\n+  <h1>To do list</h1>\n   <ul>\n       <li><button>{{tasks[0].name}}</button></li>\n   </ul>\n   `\n })\n \n export class AppComponent {\n-  title = 'To do list';\n+  title = '';\n   tasks = [\n     {\n       name: \"Angular introduction\",\n       done: false,\n"
                },
                {
                    "date": 1701855993616,
                    "content": "Index: \n===================================================================\n--- \n+++ \n@@ -11,9 +11,8 @@\n   `\n })\n \n export class AppComponent {\n-  title = '';\n   tasks = [\n     {\n       name: \"Angular introduction\",\n       done: false,\n"
                },
                {
                    "date": 1701856043872,
                    "content": "Index: \n===================================================================\n--- \n+++ \n@@ -3,9 +3,9 @@\n @Component({\n   selector: 'app-root',\n   standalone: true,\n   template: `\n-  <h1>To do list</h1>\n+  <h1 class=\"text-orange-500 bg-black py-4 text-xl text-center\">To do list</h1>\n   <ul>\n       <li><button>{{tasks[0].name}}</button></li>\n   </ul>\n   `\n"
                },
                {
                    "date": 1701856068390,
                    "content": "Index: \n===================================================================\n--- \n+++ \n@@ -3,9 +3,11 @@\n @Component({\n   selector: 'app-root',\n   standalone: true,\n   template: `\n-  <h1 class=\"text-orange-500 bg-black py-4 text-xl text-center\">To do list</h1>\n+  <h1 class=\"text-orange-500 bg-black py-4 text-xl text-center\">\n+    To do list\n+  </h1>\n   <ul>\n       <li><button>{{tasks[0].name}}</button></li>\n   </ul>\n   `\n"
                },
                {
                    "date": 1701856094592,
                    "content": "Index: \n===================================================================\n--- \n+++ \n@@ -6,8 +6,9 @@\n   template: `\n   <h1 class=\"text-orange-500 bg-black py-4 text-xl text-center\">\n     To do list\n   </h1>\n+  \n   <ul>\n       <li><button>{{tasks[0].name}}</button></li>\n   </ul>\n   `\n"
                },
                {
                    "date": 1701856149491,
                    "content": "Index: \n===================================================================\n--- \n+++ \n@@ -8,9 +8,11 @@\n     To do list\n   </h1>\n   \n   <ul>\n-      <li><button>{{tasks[0].name}}</button></li>\n+      <li>\n+        <button>{{tasks[0].name}}</button>\n+      </li>\n   </ul>\n   `\n })\n \n"
                },
                {
                    "date": 1701856206353,
                    "content": "Index: \n===================================================================\n--- \n+++ \n@@ -9,9 +9,9 @@\n   </h1>\n   \n   <ul>\n       <li>\n-        <button>{{tasks[0].name}}</button>\n+        <button class=\"{{ tasks[0].done ? 'line-through' : '' }}\">{{tasks[0].name}}</button>\n       </li>\n   </ul>\n   `\n })\n"
                }
            ],
            "date": 1701855347807,
            "name": "Commit-0",
            "content": "import { Component } from '@angular/core';\n\n@Component({\n  selector: 'app-root',\n  standalone: true,\n  template: `<h1>Welcome to {{title}}!</h1>`\n})\n\nexport class AppComponent {\n  title = '01-components-basics';\n}\n"
        }
    ]
}